ocdiff-0.0.33.dist-info/RECORD
ocdiff-0.0.33.dist-info/WHEEL
ocdiff-0.0.33.dist-info/entry_points.txt
ocdiff-0.0.33.dist-info/METADATA
ocdiff-0.0.33.dist-info/licenses/LICENSE
ocdiff/__init__.pyi
ocdiff/ocdiff.cpython-313-darwin.so
ocdiff/__init__.py
ocdiff/cli.py
ocdiff/py.typed
ocdiff/helpers.py
