Metadata-Version: 2.3
Name: ocdiff
Version: 0.0.33
Classifier: Programming Language :: Python
Requires-Dist: maturin ==1.7.4 ; extra == 'dev'
Requires-Dist: pytest ==7.* ; extra == 'dev'
Requires-Dist: mypy ==1.6.* ; extra == 'dev'
Requires-Dist: pip ==24.2 ; extra == 'dev'
Requires-Dist: pytest >=7.0 ; extra == 'test'
Provides-Extra: dev
Provides-Extra: test
License-File: LICENSE
Summary: difftastic Python wrapper
Keywords: diff
Author: Oliver Russell <ojhrussell@gmail.com>
Author-email: Oliver Russell <ojhrussell@gmail.com>
Maintainer-email: Oliver Russell <ojhrussell@gmail.com>
Requires-Python: >=3.11
Project-URL: homepage, https://github.com/leontrolski/ocdiff
Project-URL: documentation, https://github.com/leontrolski/ocdiff
Project-URL: repository, https://github.com/leontrolski/ocdiff.git
